sped_parser/__init__.py
sped_parser/compare.py
sped_parser/nodes.py
sped_parser/record_relations.py
sped_parser-0.2.1.dist-info/LICENSE
sped_parser-0.2.1.dist-info/WHEEL
sped_parser-0.2.1.dist-info/METADATA
sped_parser-0.2.1.dist-info/RECORD
